ncomp/__init__.py
ncomp/cli.py
ncomp-0.1.0.dist-info/entry_points.txt
ncomp-0.1.0.dist-info/LICENSE
ncomp-0.1.0.dist-info/WHEEL
ncomp-0.1.0.dist-info/METADATA
ncomp-0.1.0.dist-info/RECORD
