Metadata-Version: 2.1
Name: ncomp
Version: 0.1.0
Summary: A wrapper for docker-compose that adds a network to all services.
Author-email: Stephan Fitzpatrick <knowsuchagency@gmail.com>
Classifier: License :: OSI Approved :: MIT License
Requires-Dist: docker~=6.1
Requires-Dist: pyyaml~=6.0
